CHANGES
LICENSE
MANIFEST.in
flask_forward.py
setup.cfg
setup.py
Flask_Forward.egg-info/PKG-INFO
Flask_Forward.egg-info/SOURCES.txt
Flask_Forward.egg-info/dependency_links.txt
Flask_Forward.egg-info/not-zip-safe
Flask_Forward.egg-info/requires.txt
Flask_Forward.egg-info/top_level.txt
docs/.gitkeep
docs/Makefile
docs/conf.py
docs/index.rst
docs/make.bat
docs/_themes/.git
docs/_themes/.gitignore
docs/_themes/LICENSE
docs/_themes/README
docs/_themes/flask_theme_support.py
docs/_themes/flask/layout.html
docs/_themes/flask/relations.html
docs/_themes/flask/theme.conf
docs/_themes/flask/static/flasky.css_t
docs/_themes/flask/static/small_flask.css
docs/_themes/flask_small/layout.html
docs/_themes/flask_small/theme.conf
docs/_themes/flask_small/static/flasky.css_t