Metadata-Version: 1.1
Name: Flask-Forward
Version: 0.1.0
Summary: Flask-Forward extension provides auto discovery,                  prioritization and rendering of template for Flask                  based on endpoint
Home-page: https://github.com/saikocat/flask-forward
Author: Nguyen Duc Hoa
Author-email: hoameomu@gmail.com
License: MIT
Platform: any
Classifier: Development Status :: 4 - Beta
Classifier: Environment :: Web Environment
Classifier: Intended Audience :: Developers
Classifier: License :: OSI Approved :: MIT License
Classifier: Operating System :: OS Independent
Classifier: Programming Language :: Python
Classifier: Topic :: Internet :: WWW/HTTP :: Dynamic Content
Classifier: Topic :: Software Development :: Libraries :: Python Modules
